{"data":[
{"domain":"benbernstein.eth"},
{"domain":"benberry.eth"},
{"domain":"benbest.eth"},
{"domain":"benbfisher.eth"},
{"domain":"benbi.eth"},
{"domain":"benbirdly.eth"},
{"domain":"benbit.eth"},
{"domain":"benbj.eth"},
{"domain":"benblack.eth"},
{"domain":"benblackburn.eth"},
{"domain":"benblenner.eth"},
{"domain":"benblute.eth"},
{"domain":"benbo.eth"},
{"domain":"benbob.eth"},
{"domain":"benboben.eth"},
{"domain":"benbodhi.eth"},
{"domain":"benboi.eth"},
{"domain":"benborba.eth"},
{"domain":"benbowden.eth"},
{"domain":"benbroca.eth"},
{"domain":"benbrooks.eth"},
{"domain":"benbrosnan.eth"},
{"domain":"benbrry.eth"},
{"domain":"benbruder.eth"},
{"domain":"benbruno.eth"},
{"domain":"benbuchanan.eth"},
{"domain":"benbucihanasmazam.eth"},
{"domain":"benbuddeh.eth"},
{"domain":"benburns.eth"},
{"domain":"benbush.eth"},
{"domain":"benc777.eth"},
{"domain":"bencamara.eth"},
{"domain":"bencao.eth"},
{"domain":"bencedolin.eth"},
{"domain":"benceivanyi.eth"},
{"domain":"bencethereal.eth"},
{"domain":"benceus.eth"},
{"domain":"bencevarga.eth"},
{"domain":"benchaaan.eth"},
{"domain":"benchagra.eth"},
{"domain":"benchai.eth"},
{"domain":"benchan.eth"},
{"domain":"benchcard.eth"},
{"domain":"benchen.eth"},
{"domain":"bencheng.eth"},
{"domain":"bencherian.eth"},
{"domain":"bencheung.eth"},
{"domain":"benchi001.eth"},
{"domain":"benchilla.eth"},
{"domain":"benchjeweler.eth"},
{"domain":"benchkelp.eth"},
{"domain":"benchmarc.eth"},
{"domain":"benchoong.eth"},
{"domain":"benchsmart.eth"},
{"domain":"benchthis.eth"},
{"domain":"benchu00.eth"},
{"domain":"benchuchu.eth"},
{"domain":"benchung.eth"},
{"domain":"benchwork.eth"},
{"domain":"bencic.eth"},
{"domain":"bencils.eth"},
{"domain":"bencito.eth"},
{"domain":"bencji.eth"},
{"domain":"benclair.eth"},
{"domain":"bencmjn.eth"},
{"domain":"bencole.eth"},
{"domain":"bencong.eth"},
{"domain":"bencooper.eth"},
{"domain":"bencopter.eth"},
{"domain":"bencraig.eth"},
{"domain":"bencrowder.eth"},
{"domain":"bencrox.eth"},
{"domain":"bencryption.eth"},
{"domain":"bencullen.eth"},
{"domain":"benculpin.eth"},
{"domain":"bencurtin.eth"},
{"domain":"bency.eth"},
{"domain":"bend0ver.eth"},
{"domain":"bend3st.eth"},
{"domain":"benda.eth"},
{"domain":"bendabbin.eth"},
{"domain":"bendaman.eth"},
{"domain":"bendamj.eth"},
{"domain":"bendan.eth"},
{"domain":"bendarwish.eth"},
{"domain":"bendasilva.eth"},
{"domain":"bendav371.eth"},
{"domain":"bendavies.eth"},
{"domain":"bendavis.eth"},
{"domain":"benday.eth"},
{"domain":"benddao.eth"},
{"domain":"benddaobot.eth"},
{"domain":"benddaodev.eth"},
{"domain":"benddaoteam.eth"},
{"domain":"bendebucara.eth"},
{"domain":"bendegen.eth"},
{"domain":"bendel.eth"},
{"domain":"bendelaney.eth"},
{"domain":"bendelves.eth"},
{"domain":"bendenia.eth"},
{"domain":"bender01.eth"},
{"domain":"bender1.eth"},
{"domain":"bender777z.eth"},
{"domain":"benderdev.eth"},
{"domain":"benderk.eth"},
{"domain":"bendermind.eth"},
{"domain":"benders.eth"},
{"domain":"bendersej.eth"},
{"domain":"bendertherobot.eth"},
{"domain":"benderz.eth"},
{"domain":"bendetta.eth"},
{"domain":"bendey.eth"},
{"domain":"bendgirl.eth"},
{"domain":"bendhomesnow.eth"},
{"domain":"bendi.eth"},
{"domain":"bendickey.eth"},
{"domain":"bendigenous.eth"},
{"domain":"bendlm.eth"},
{"domain":"bendobbrick.eth"},
{"domain":"bendoetzer.eth"},
{"domain":"bendos.eth"},
{"domain":"bendotk-vault.eth"},
{"domain":"bendover.eth"},
{"domain":"bendoverdev.eth"},
{"domain":"bendr.eth"},
{"domain":"bendragon.eth"},
{"domain":"bendreary.eth"},
{"domain":"bendroz.eth"},
{"domain":"bendthaknee.eth"},
{"domain":"bendu.eth"},
{"domain":"bendumoulin.eth"},
{"domain":"bendy.eth"},
{"domain":"bendystraw.eth"},
{"domain":"bendystraws.eth"},
{"domain":"bendzi.eth"},
{"domain":"beneat.eth"},
{"domain":"beneaththe.eth"},
{"domain":"benebla.eth"},
{"domain":"beneco.eth"},
{"domain":"benedetti.eth"},
{"domain":"benedict.eth"},
{"domain":"benedictcapaldi.eth"},
{"domain":"benedictine.eth"},
{"domain":"benedictjung.eth"},
{"domain":"benedicto.eth"},
{"domain":"benedictus.eth"},
{"domain":"benedictxvii.eth"},
{"domain":"benedikta.eth"},
{"domain":"benediktas.eth"},
{"domain":"benedixt.eth"},
{"domain":"benedmund.eth"},
{"domain":"benedwards.eth"},
{"domain":"beneeaton.eth"},
{"domain":"beneeb.eth"},
{"domain":"benef.eth"},
{"domain":"beneficemax.eth"},
{"domain":"benefitcrypto.eth"},
{"domain":"benefitmine.eth"},
{"domain":"benefitofthedao.eth"},
{"domain":"beneftea.eth"},
{"domain":"benegesserit.eth"},
{"domain":"beneisner.eth"},
{"domain":"benek.eth"},
{"domain":"benelferink.eth"},
{"domain":"benelic.eth"},
{"domain":"benelli.eth"},
{"domain":"benelliott.eth"},
{"domain":"beneone.eth"},
{"domain":"bener.eth"},
{"domain":"benergy.eth"},
{"domain":"benersing.eth"},
{"domain":"benesch.eth"},
{"domain":"benesser.eth"},
{"domain":"benestante.eth"},
{"domain":"benethminer.eth"},
{"domain":"benetlor.eth"},
{"domain":"beneverard.eth"},
{"domain":"benevity.eth"},
{"domain":"benevolent-whale.eth"},
{"domain":"benevolent.eth"},
{"domain":"benevolentspectator.eth"},
{"domain":"benface.eth"},
{"domain":"benfairclough.eth"},
{"domain":"benfarber.eth"},
{"domain":"benfathi.eth"},
{"domain":"benfeldman.eth"},
{"domain":"benferrum.eth"},
{"domain":"benfielding.eth"},
{"domain":"benfish.eth"},
{"domain":"benfleet.eth"},
{"domain":"benflocka.eth"},
{"domain":"benflorsheim.eth"},
{"domain":"benfoster.eth"},
{"domain":"benfox.eth"},
{"domain":"benframe.eth"},
{"domain":"benfrancis.eth"},
{"domain":"benfrank.eth"},
{"domain":"benfranke.eth"},
{"domain":"benfree.eth"},
{"domain":"benfreebiz.eth"},
{"domain":"benfrench.eth"},
{"domain":"benfried.eth"},
{"domain":"benfryc.eth"},
{"domain":"benft8888.eth"},
{"domain":"benftsolutions.eth"},
{"domain":"benfty.eth"},
{"domain":"benfucks.eth"},
{"domain":"benfutor.eth"},
{"domain":"beng.eth"},
{"domain":"beng266.eth"},
{"domain":"bengabbard.eth"},
{"domain":"bengaldaonft.eth"},
{"domain":"bengaliboy.eth"},
{"domain":"bengallagher.eth"},
{"domain":"bengalsnut30.eth"},
{"domain":"bengan.eth"},
{"domain":"bengarcia.eth"},
{"domain":"bengarrison.eth"},
{"domain":"bengb.eth"},
{"domain":"bengbeng.eth"},
{"domain":"benge.eth"},
{"domain":"bengeblaze.eth"},
{"domain":"bengel.eth"},
{"domain":"bengelass.eth"},
{"domain":"bengenix.eth"},
{"domain":"bengeorgie.eth"},
{"domain":"benger.eth"},
{"domain":"bengerber.eth"},
{"domain":"bengetrol.eth"},
{"domain":"bengiannelli.eth"},
{"domain":"bengii.eth"},
{"domain":"bengilbert.eth"},
{"domain":"bengillin.eth"},
{"domain":"benginahmad.eth"},
{"domain":"bengio.eth"},
{"domain":"benglass.eth"},
{"domain":"bengoh.eth"},
{"domain":"bengolden.eth"},
{"domain":"bengordon.eth"},
{"domain":"bengoro.eth"},
{"domain":"bengottfried.eth"},
{"domain":"bengrassini.eth"},
{"domain":"bengreen.eth"},
{"domain":"bengreen927.eth"},
{"domain":"bengreenberg.eth"},
{"domain":"bengreenwood.eth"},
{"domain":"bengregory.eth"},
{"domain":"bengreve.eth"},
{"domain":"bengrobler.eth"},
{"domain":"bengross.eth"},
{"domain":"bengrosse.eth"},
{"domain":"bengrossman.eth"},
{"domain":"benguedj.eth"},
{"domain":"benguigs.eth"},
{"domain":"bengusberg.eth"},
{"domain":"bengx.eth"},
{"domain":"bengy.eth"},
{"domain":"bengzon.eth"},
{"domain":"benh20.eth"},
{"domain":"benhadley.eth"},
{"domain":"benhaley.eth"},
{"domain":"benhalverson.eth"},
{"domain":"benhammer.eth"},
{"domain":"benharbort.eth"},
{"domain":"benhardin.eth"},
{"domain":"benharmanus.eth"},
{"domain":"benharrison.eth"},
{"domain":"benharvey.eth"},
{"domain":"benhc.eth"},
{"domain":"benhekker.eth"},
{"domain":"benhendricks.eth"},
{"domain":"benherbertson.eth"},
{"domain":"benhh.eth"},
{"domain":"benhick92.eth"},
{"domain":"benhirons.eth"},
{"domain":"benhoelzl.eth"},
{"domain":"benhoffman.eth"},
{"domain":"benholguin.eth"},
{"domain":"benholland.eth"},
{"domain":"benhopper.eth"},
{"domain":"benhovell.eth"},
{"domain":"benhq.eth"},
{"domain":"benhsu.eth"},
{"domain":"benhu.eth"},
{"domain":"benhughes.eth"},
{"domain":"benhundreds.eth"},
{"domain":"benhurdonethat.eth"},
{"domain":"benhurley.eth"},
{"domain":"benhurs.eth"},
{"domain":"benhurst.eth"},
{"domain":"beni.eth"},
{"domain":"beniaminnetaniahu.eth"},
{"domain":"beniamino.eth"},
{"domain":"beniaminogrande.eth"},
{"domain":"beniamintopa.eth"},
{"domain":"benibachi.eth"},
{"domain":"beniben.eth"},
{"domain":"benibischof.eth"},
{"domain":"benig0218.eth"},
{"domain":"benigarc.eth"},
{"domain":"benii.eth"},
{"domain":"benijob.eth"},
{"domain":"benim.eth"},
{"domain":"benimble.eth"},
{"domain":"benimitnetan.eth"},
{"domain":"benin.eth"},
{"domain":"beninaboki.eth"},
{"domain":"beninasiri.eth"},
{"domain":"beninawai.eth"},
{"domain":"beninbronze.eth"},
{"domain":"beninem.eth"},
{"domain":"benip.eth"},
{"domain":"benipayo.eth"},
{"domain":"benipsen.eth"},
{"domain":"benique.eth"},
{"domain":"benit.eth"},
{"domain":"benit0.eth"},
{"domain":"benitah.eth"},
{"domain":"benitch.eth"},
{"domain":"benitez.eth"},
{"domain":"benithejet.eth"},
{"domain":"benito.eth"},
{"domain":"benitoart.eth"},
{"domain":"benitobertelli.eth"},
{"domain":"benitoblanco.eth"},
{"domain":"benitofisher.eth"},
{"domain":"benitomilan.eth"},
{"domain":"benitomusolini.eth"},
{"domain":"benivel.eth"},
{"domain":"benividivicii.eth"},
{"domain":"benizm.eth"},
{"domain":"benj0x.eth"},
{"domain":"benjaaam.eth"},
{"domain":"benjaam.eth"},
{"domain":"benjabo.eth"},
{"domain":"benjabrajovic.eth"},
{"domain":"benjabrooks.eth"},
{"domain":"benjabutt.eth"},
{"domain":"benjack.eth"},
{"domain":"benjack01.eth"},
{"domain":"benjaffer.eth"},
{"domain":"benjafrias.eth"},
{"domain":"benjafrog.eth"},
{"domain":"benjafrogvault.eth"},
{"domain":"benjahman.eth"},
{"domain":"benjalimm.eth"},
{"domain":"benjamais.eth"},
{"domain":"benjames.eth"},
{"domain":"benjamesvault.eth"},
{"domain":"benjameta.eth"},
{"domain":"benjamillion.eth"},
{"domain":"benjamimic.eth"},
{"domain":"benjamin.eth"},
{"domain":"benjamin23.eth"},
{"domain":"benjaminancona.eth"},
{"domain":"benjaminang.eth"},
{"domain":"benjaminazoulay.eth"},
{"domain":"benjaminbardou.eth"},
{"domain":"benjaminbenitez.eth"},
{"domain":"benjaminberesford.eth"},
{"domain":"benjaminberry.eth"},
{"domain":"benjaminbollen.eth"},
{"domain":"benjaminbor.eth"},
{"domain":"benjaminbot.eth"},
{"domain":"benjaminbrand.eth"},
{"domain":"benjaminbrey.eth"},
{"domain":"benjaminbudden.eth"},
{"domain":"benjaminbutton.eth"},
{"domain":"benjamincameronbaldwin.eth"},
{"domain":"benjamincburns.eth"},
{"domain":"benjaminchait.eth"},
{"domain":"benjaminchen.eth"},
{"domain":"benjaminchodroff.eth"},
{"domain":"benjaminclymer.eth"},
{"domain":"benjamincout.eth"},
{"domain":"benjamindover.eth"},
{"domain":"benjaminfritz.eth"},
{"domain":"benjaminfulk.eth"},
{"domain":"benjaminfunk.eth"},
{"domain":"benjamingalindo.eth"},
{"domain":"benjamingeorge.eth"},
{"domain":"benjamingoh.eth"},
{"domain":"benjamingoldberg.eth"},
{"domain":"benjamingordon.eth"},
{"domain":"benjamingrandi.eth"},
{"domain":"benjaminhaber.eth"},
{"domain":"benjaminhan.eth"},
{"domain":"benjaminhardman.eth"},
{"domain":"benjaminharley.eth"},
{"domain":"benjaminhilborn.eth"},
{"domain":"benjaminhuang.eth"},
{"domain":"benjaminion.eth"},
{"domain":"benjaminjacobs.eth"},
{"domain":"benjaminjones.eth"},
{"domain":"benjaminlauren.eth"},
{"domain":"benjaminleb.eth"},
{"domain":"benjaminlin.eth"},
{"domain":"benjaminlinford.eth"},
{"domain":"benjaminlong.eth"},
{"domain":"benjaminmaldonado.eth"},
{"domain":"benjaminmercer.eth"},
{"domain":"benjaminness.eth"},
{"domain":"benjaminpbaker.eth"},
{"domain":"benjaminpeter.eth"},
{"domain":"benjaminprune.eth"},
{"domain":"benjaminrost.eth"},
{"domain":"benjaminsar.eth"},
{"domain":"benjaminscartel.eth"},
{"domain":"benjaminschultejohann.eth"},
{"domain":"benjaminschunk.eth"},
{"domain":"benjaminsiegal.eth"},
{"domain":"benjaminsnft.eth"},
{"domain":"benjaminspink.eth"},
{"domain":"benjaminstoll.eth"},
{"domain":"benjaminstrong.eth"},
{"domain":"🅱️enjaminsu.eth"},
{"domain":"benjaminsymons.eth"},
{"domain":"benjamintang.eth"},
{"domain":"benjamintank.eth"},
{"domain":"benjamintay.eth"},
{"domain":"benjamints.eth"},
{"domain":"benjaminvickers.eth"},
{"domain":"benjaminwalker.eth"},
{"domain":"benjaminwallace.eth"},
{"domain":"benjaminwest.eth"},
{"domain":"benjaminwootton.eth"},
{"domain":"benjaminwunsch.eth"},
{"domain":"benjaminyap.eth"},
{"domain":"benjammin.eth"},
{"domain":"benjamo.eth"},
{"domain":"benjamoon.eth"},
{"domain":"benjamyn.eth"},
{"domain":"benjanik.eth"},
{"domain":"benjap.eth"},
{"domain":"benjatorrero.eth"},
{"domain":"benjay.eth"},
{"domain":"benjchan.eth"},
{"domain":"benje.eth"},
{"domain":"benjeaster.eth"},
{"domain":"benjee.eth"},
{"domain":"benjeezy.eth"},
{"domain":"benjeh.eth"},
{"domain":"benjelloun.eth"},
{"domain":"benjemen.eth"},
{"domain":"benjen.eth"},
{"domain":"benjerrie.eth"},
{"domain":"benjey.eth"},
{"domain":"benjeyyy.eth"},
{"domain":"benji.eth"},
{"domain":"benji45645.eth"},
{"domain":"benji8888.eth"},
{"domain":"benjiaming.eth"},
{"domain":"benjibagz.eth"},
{"domain":"benjibannanas.eth"},
{"domain":"benjibendover.eth"},
{"domain":"benjibenimoto.eth"},
{"domain":"benjiblue.eth"},
{"domain":"benjiboy.eth"},
{"domain":"benjicohen.eth"},
{"domain":"benjiconnell.eth"},
{"domain":"benjicox.eth"},
{"domain":"benjid.eth"},
{"domain":"benjiduong.eth"},
{"domain":"benjieescobar.eth"},
{"domain":"benjiefranks.eth"},
{"domain":"benjifdev.eth"},
{"domain":"benjihanspree.eth"},
{"domain":"benjii.eth"},
{"domain":"benjiii.eth"},
{"domain":"benjiinu.eth"},
{"domain":"benjij.eth"},
{"domain":"benjik.eth"},
{"domain":"benjikadwallet.eth"},
{"domain":"benjilanyado.eth"},
{"domain":"benjileibowitz.eth"},
{"domain":"benjimack.eth"},
{"domain":"benjimackvault.eth"},
{"domain":"benjiming.eth"},
{"domain":"benjimon.eth"},
{"domain":"benjin.eth"},
{"domain":"benjinomics.eth"},
{"domain":"benjioh5.eth"},
{"domain":"benjiprice.eth"},
{"domain":"benjirodev.eth"},
{"domain":"benjistein.eth"},
{"domain":"benjisvault.eth"},
{"domain":"benjit.eth"},
{"domain":"benjitaylor.eth"},
{"domain":"benjito.eth"},
{"domain":"benjix21.eth"},
{"domain":"benjk6.eth"},
{"domain":"benjmestrallet.eth"},
{"domain":"benjo990.eth"},
{"domain":"benjoc.eth"},
{"domain":"benjochem.eth"},
{"domain":"benjohnson.eth"},
{"domain":"benjohnston.eth"},
{"domain":"benjonniaux.eth"},
{"domain":"benjonson.eth"},
{"domain":"benjordan.eth"}
]}