{"data":[
{"domain":"airshiprebekah.eth"},
{"domain":"airside.eth"},
{"domain":"airsipani.eth"},
{"domain":"airsnkrs.eth"},
{"domain":"airspeed.eth"},
{"domain":"airsports.eth"},
{"domain":"airss.eth"},
{"domain":"airstack.eth"},
{"domain":"airstat.eth"},
{"domain":"airsub.eth"},
{"domain":"airsuv.eth"},
{"domain":"airtell.eth"},
{"domain":"airtime.eth"},
{"domain":"airtist.eth"},
{"domain":"airtomson.eth"},
{"domain":"airton.eth"},
{"domain":"airtoroutreach.eth"},
{"domain":"airtorprotocol.eth"},
{"domain":"airtrack.eth"},
{"domain":"airtune.eth"},
{"domain":"airvan.eth"},
{"domain":"airvault.eth"},
{"domain":"airvey.eth"},
{"domain":"airvoid.eth"},
{"domain":"airwaive.eth"},
{"domain":"airwalk009.eth"},
{"domain":"airwar.eth"},
{"domain":"airwarden.eth"},
{"domain":"airway.eth"},
{"domain":"airwolf.eth"},
{"domain":"airwolfltd.eth"},
{"domain":"airwolfspace.eth"},
{"domain":"airwreck.eth"},
{"domain":"airyeezy.eth"},
{"domain":"airyland.eth"},
{"domain":"airyvault.eth"},
{"domain":"airywd.eth"},
{"domain":"airyxol.eth"},
{"domain":"airz.eth"},
{"domain":"airzin.eth"},
{"domain":"ais-official.eth"},
{"domain":"aisaacs.eth"},
{"domain":"aisakataiga.eth"},
{"domain":"aisapay.eth"},
{"domain":"aisar.eth"},
{"domain":"aisatoshi.eth"},
{"domain":"aiscanf.eth"},
{"domain":"aiscb.eth"},
{"domain":"aiscdeployer.eth"},
{"domain":"aischa.eth"},
{"domain":"aisearching.eth"},
{"domain":"aisforandrew.eth"},
{"domain":"aish.eth"},
{"domain":"aishaaina.eth"},
{"domain":"aishaburgos.eth"},
{"domain":"aishadigo.eth"},
{"domain":"aishahbloom.eth"},
{"domain":"aishanatasha.eth"},
{"domain":"aishang.eth"},
{"domain":"aishanghaimen.eth"},
{"domain":"aishao.eth"},
{"domain":"aishaoamode.eth"},
{"domain":"aishasalman.eth"},
{"domain":"aishatugo.eth"},
{"domain":"aishe.eth"},
{"domain":"aishia.eth"},
{"domain":"aishiba.eth"},
{"domain":"aishik.eth"},
{"domain":"aishine.eth"},
{"domain":"aishine313.eth"},
{"domain":"aishite773.eth"},
{"domain":"aishleyk.eth"},
{"domain":"aishlia.eth"},
{"domain":"aishoesdev.eth"},
{"domain":"aishwarrior.eth"},
{"domain":"aishwary.eth"},
{"domain":"aishwarya-kamraj.eth"},
{"domain":"aishwaryasaha.eth"},
{"domain":"aisiji.eth"},
{"domain":"aisiki.eth"},
{"domain":"aisilu.eth"},
{"domain":"aisis.eth"},
{"domain":"aisix.eth"},
{"domain":"aiskill.eth"},
{"domain":"aisky.eth"},
{"domain":"aislandart.eth"},
{"domain":"aisle24market.eth"},
{"domain":"aisle3.eth"},
{"domain":"aisling.eth"},
{"domain":"aismartchain.eth"},
{"domain":"aismartchaindevolepment.eth"},
{"domain":"aismartchainmarketing.eth"},
{"domain":"aisocialnet.eth"},
{"domain":"aisop.eth"},
{"domain":"aisoulnft.eth"},
{"domain":"aisouls.eth"},
{"domain":"aissas.eth"},
{"domain":"aistarter.eth"},
{"domain":"aistarwars.eth"},
{"domain":"aistation.eth"},
{"domain":"aisten.eth"},
{"domain":"aistep.eth"},
{"domain":"aisthesis85.eth"},
{"domain":"aisthisi.eth"},
{"domain":"aistobe.eth"},
{"domain":"aistrategies.eth"},
{"domain":"aistrich.eth"},
{"domain":"aistrong.eth"},
{"domain":"aistyle.eth"},
{"domain":"aisu.eth"},
{"domain":"aisuro.eth"},
{"domain":"aisuru.eth"},
{"domain":"aiswap.eth"},
{"domain":"ait.eth"},
{"domain":"aitaissa.eth"},
{"domain":"aitakeover.eth"},
{"domain":"aitalkinboutpractice.eth"},
{"domain":"aitao.eth"},
{"domain":"aitarf.eth"},
{"domain":"aitata.eth"},
{"domain":"aitazaz.eth"},
{"domain":"aitchbee71.eth"},
{"domain":"aite.eth"},
{"domain":"aitech.eth"},
{"domain":"aitechdeployer.eth"},
{"domain":"aitesting.eth"},
{"domain":"aitexas.eth"},
{"domain":"aitgsamurai.eth"},
{"domain":"aithal.eth"},
{"domain":"aitheanswer.eth"},
{"domain":"aithecrossover.eth"},
{"domain":"aithereal.eth"},
{"domain":"aithereumdeployer.eth"},
{"domain":"aithinkboi.eth"},
{"domain":"aithne.eth"},
{"domain":"aitibi.eth"},
{"domain":"aitik.eth"},
{"domain":"aitjcize.eth"},
{"domain":"aitn.eth"},
{"domain":"aito.eth"},
{"domain":"aitom7.eth"},
{"domain":"aitorarteta.eth"},
{"domain":"aitorbarina.eth"},
{"domain":"aitorgrandes.eth"},
{"domain":"aitori.eth"},
{"domain":"aitravis.eth"},
{"domain":"aitso.eth"},
{"domain":"aitsuno.eth"},
{"domain":"aitushar.eth"},
{"domain":"aiuehara.eth"},
{"domain":"aiueo.eth"},
{"domain":"aiukl.eth"},
{"domain":"aiuniverse.eth"},
{"domain":"aius-.eth"},
{"domain":"aiuser1.eth"},
{"domain":"aiuyanna.eth"},
{"domain":"aivan.eth"},
{"domain":"aivarlonewolff.eth"},
{"domain":"aivaryamal.eth"},
{"domain":"aivax.eth"},
{"domain":"aivers.eth"},
{"domain":"aivie1231.eth"},
{"domain":"aivilo.eth"},
{"domain":"aivipday.eth"},
{"domain":"aivisual.eth"},
{"domain":"aivor.eth"},
{"domain":"aivorygaw.eth"},
{"domain":"aivox.eth"},
{"domain":"aivtalik.eth"},
{"domain":"aivxgodlike.eth"},
{"domain":"aiwalker.eth"},
{"domain":"aiwallet.eth"},
{"domain":"aiwalletdeployer.eth"},
{"domain":"aiwan.eth"},
{"domain":"aiwangye.eth"},
{"domain":"aiwas.eth"},
{"domain":"aiwaska.eth"},
{"domain":"aiway.eth"},
{"domain":"aiwobiezou.eth"},
{"domain":"aiword.eth"},
{"domain":"aiwtgdesigns.eth"},
{"domain":"aix888.eth"},
{"domain":"aixduo.eth"},
{"domain":"aixiaoyan.eth"},
{"domain":"aixie.eth"},
{"domain":"aixige.eth"},
{"domain":"aixixx.eth"},
{"domain":"aixuexi.eth"},
{"domain":"aixuexicc.eth"},
{"domain":"aixumara.eth"},
{"domain":"aixverse.eth"},
{"domain":"aixxw.eth"},
{"domain":"aiyah.eth"},
{"domain":"aiyak.eth"},
{"domain":"aiyana.eth"},
{"domain":"aiyash.eth"},
{"domain":"aiyeo.eth"},
{"domain":"aiyibao.eth"},
{"domain":"aiyidan.eth"},
{"domain":"aiyo.eth"},
{"domain":"aiyor.eth"},
{"domain":"aiyou-iu.eth"},
{"domain":"aiyoufd.eth"},
{"domain":"aiyu.eth"},
{"domain":"aiyuan.eth"},
{"domain":"aiyubei.eth"},
{"domain":"aiyuyu.eth"},
{"domain":"aiz3n.eth"},
{"domain":"aiza.eth"},
{"domain":"aizaditabar.eth"},
{"domain":"aizan.eth"},
{"domain":"aizaya.eth"},
{"domain":"aizaz.eth"},
{"domain":"aizen.eth"},
{"domain":"aizenfx.eth"},
{"domain":"aizensosuke.eth"},
{"domain":"aizenwes.eth"},
{"domain":"aizer.eth"},
{"domain":"aizhanka.eth"},
{"domain":"aizhenjiu.eth"},
{"domain":"aizhikov.eth"},
{"domain":"aizkolari.eth"},
{"domain":"aizlee.eth"},
{"domain":"aizome.eth"},
{"domain":"aizomξ.eth"},
{"domain":"aizucsl.eth"},
{"domain":"aizzy.eth"},
{"domain":"aiィー⤴︎🧬tsumugiai.eth"},
{"domain":"aj_0033.eth"},
{"domain":"aj_money.eth"},
{"domain":"aj-fk.eth"},
{"domain":"aj.eth"},
{"domain":"aj0021.eth"},
{"domain":"aj013.eth"},
{"domain":"aj1.eth"},
{"domain":"aj182.eth"},
{"domain":"aj1collector.eth"},
{"domain":"aj2017.eth"},
{"domain":"aj222.eth"},
{"domain":"aj247.eth"},
{"domain":"aj29.eth"},
{"domain":"aj555.eth"},
{"domain":"aja.eth"},
{"domain":"ajaadey.eth"},
{"domain":"ajaayx.eth"},
{"domain":"ajackman.eth"},
{"domain":"ajada.eth"},
{"domain":"ajadams.eth"},
{"domain":"ajadavis.eth"},
{"domain":"ajadonai.eth"},
{"domain":"ajadudraws.eth"},
{"domain":"ajafari.eth"},
{"domain":"ajaff.eth"},
{"domain":"ajairaj.eth"},
{"domain":"ajak.eth"},
{"domain":"ajalee.eth"},
{"domain":"ajalix.eth"},
{"domain":"ajamjoom.eth"},
{"domain":"ajamos.eth"},
{"domain":"ajand.eth"},
{"domain":"ajandrews.eth"},
{"domain":"ajang.eth"},
{"domain":"ajaniphoto.eth"},
{"domain":"ajap1958.eth"},
{"domain":"ajarawpiatek.eth"},
{"domain":"ajarov.eth"},
{"domain":"ajascha.eth"},
{"domain":"ajasont.eth"},
{"domain":"ajasra.eth"},
{"domain":"ajax2500.eth"},
{"domain":"ajax3d.eth"},
{"domain":"ajax433.eth"},
{"domain":"ajaxafc.eth"},
{"domain":"ajaxdao.eth"},
{"domain":"ajaxshexl.eth"},
{"domain":"ajaxx.eth"},
{"domain":"ajay.eth"},
{"domain":"ajayahdiyat.eth"},
{"domain":"ajayan.eth"},
{"domain":"ajayarora.eth"},
{"domain":"ajaybala.eth"},
{"domain":"ajayeztt.eth"},
{"domain":"ajaygandhi.eth"},
{"domain":"ajayghale.eth"},
{"domain":"ajaygill.eth"},
{"domain":"ajayi.eth"},
{"domain":"ajayjadeja.eth"},
{"domain":"ajayjoshi.eth"},
{"domain":"ajaykhanna.eth"},
{"domain":"ajaykumar.eth"},
{"domain":"ajaykumarvemuri.eth"},
{"domain":"ajaykumaryt.eth"},
{"domain":"ajaym.eth"},
{"domain":"ajaymittal.eth"},
{"domain":"ajayn.eth"},
{"domain":"ajaynayak.eth"},
{"domain":"ajayny.eth"},
{"domain":"ajayp.eth"},
{"domain":"ajaypal.eth"},
{"domain":"ajayprakash.eth"},
{"domain":"ajays97.eth"},
{"domain":"ajaysh.eth"},
{"domain":"ajaysharma.eth"},
{"domain":"ajaysingal.eth"},
{"domain":"ajayt.eth"},
{"domain":"ajaythiara.eth"},
{"domain":"ajaytr.eth"},
{"domain":"ajaytvault.eth"},
{"domain":"ajayv.eth"},
{"domain":"ajayvasisht.eth"},
{"domain":"ajazrubz.eth"},
{"domain":"ajb.eth"},
{"domain":"ajb10.eth"},
{"domain":"ajb413.eth"},
{"domain":"ajberni.eth"},
{"domain":"ajbosch.eth"},
{"domain":"ajburner.eth"},
{"domain":"ajc.eth"},
{"domain":"ajc254.eth"},
{"domain":"ajchatham.eth"},
{"domain":"ajclarke.eth"},
{"domain":"ajcorrado.eth"},
{"domain":"ajcrmr.eth"},
{"domain":"ajcrowley.eth"},
{"domain":"ajcrypto456.eth"},
{"domain":"ajcwebdev.eth"},
{"domain":"ajcx8.eth"},
{"domain":"ajd401.eth"},
{"domain":"ajdao.eth"},
{"domain":"ajdavis.eth"},
{"domain":"ajder.eth"},
{"domain":"ajdiaz.eth"},
{"domain":"ajdiii.eth"},
{"domain":"ajdillon28.eth"},
{"domain":"ajdimarucot.eth"},
{"domain":"ajdonzo.eth"},
{"domain":"ajdp13.eth"},
{"domain":"ajdubs.eth"},
{"domain":"ajduran.eth"},
{"domain":"aje.eth"},
{"domain":"ajebe.eth"},
{"domain":"ajebo.eth"},
{"domain":"ajeetmaurya.eth"},
{"domain":"ajeetsdream.eth"},
{"domain":"ajehrenberg.eth"},
{"domain":"ajeje.eth"},
{"domain":"ajema.eth"},
{"domain":"ajemian.eth"},
{"domain":"ajenft94.eth"},
{"domain":"ajenks.eth"},
{"domain":"ajeremy.eth"},
{"domain":"ajes.eth"},
{"domain":"ajeserjose.eth"},
{"domain":"ajex.eth"},
{"domain":"ajferris.eth"},
{"domain":"ajfoundation.eth"},
{"domain":"ajfrank.eth"},
{"domain":"ajfreestone.eth"},
{"domain":"ajfunds.eth"},
{"domain":"ajgnet.eth"},
{"domain":"ajgodham.eth"},
{"domain":"ajgodzilla.eth"},
{"domain":"ajgoldman.eth"},
{"domain":"ajgvault.eth"},
{"domain":"ajh.eth"},
{"domain":"ajh13.eth"},
{"domain":"ajhar.eth"},
{"domain":"ajhay12.eth"},
{"domain":"ajholland.eth"},
{"domain":"ajiaco.eth"},
{"domain":"ajian55.eth"},
{"domain":"ajibola.eth"},
{"domain":"ajibolatyrah09.eth"},
{"domain":"ajicon.eth"},
{"domain":"ajie.eth"},
{"domain":"ajie888.eth"},
{"domain":"ajielu.eth"},
{"domain":"ajieni.eth"},
{"domain":"ajier.eth"},
{"domain":"ajifogi.eth"},
{"domain":"ajikan.eth"},
{"domain":"ajimaulana.eth"},
{"domain":"ajimmyslife.eth"},
{"domain":"ajin.eth"},
{"domain":"ajinde.eth"},
{"domain":"ajing.eth"},
{"domain":"ajinkya.eth"},
{"domain":"ajinkyaj.eth"},
{"domain":"ajinkyamulay.eth"},
{"domain":"ajinomotoo.eth"},
{"domain":"ajinx.eth"},
{"domain":"ajiro.eth"},
{"domain":"ajit.eth"},
{"domain":"ajitagarkar.eth"},
{"domain":"ajitama.eth"},
{"domain":"ajitchouhan.eth"},
{"domain":"ajith.eth"},
{"domain":"ajitha.eth"},
{"domain":"ajithjunior.eth"},
{"domain":"ajithk.eth"},
{"domain":"ajithkumarart.eth"},
{"domain":"ajitkoti.eth"},
{"domain":"ajjday.eth"},
{"domain":"ajjnna.eth"},
{"domain":"ajjo8.eth"},
{"domain":"ajjoshi.eth"},
{"domain":"ajk517.eth"},
{"domain":"ajkartgallery.eth"},
{"domain":"ajkdnf.eth"},
{"domain":"ajkhah.eth"},
{"domain":"ajknft.eth"},
{"domain":"ajkrypto.eth"},
{"domain":"ajl.eth"},
{"domain":"ajlara.eth"},
{"domain":"ajlaw.eth"},
{"domain":"ajlawrence.eth"},
{"domain":"ajlee.eth"},
{"domain":"ajlew.eth"},
{"domain":"ajlive.eth"},
{"domain":"ajllaguno.eth"},
{"domain":"ajlone.eth"},
{"domain":"ajlopez.eth"},
{"domain":"ajm.eth"},
{"domain":"ajmail.eth"},
{"domain":"ajmalafif.eth"},
{"domain":"ajmall.eth"},
{"domain":"ajmancini.eth"},
{"domain":"ajmannft.eth"},
{"domain":"ajmay.eth"},
{"domain":"ajmedina.eth"},
{"domain":"ajmeer.eth"},
{"domain":"ajmeister.eth"},
{"domain":"ajmen.eth"},
{"domain":"ajmhidrulica.eth"},
{"domain":"ajmighty.eth"},
{"domain":"ajmints.eth"},
{"domain":"ajmira.eth"},
{"domain":"ajmitchell25.eth"},
{"domain":"ajmnlt.eth"},
{"domain":"ajmoney.eth"},
{"domain":"ajmoon.eth"},
{"domain":"ajmortega.eth"},
{"domain":"ajn36.eth"},
{"domain":"ajna.eth"},
{"domain":"ajna6.eth"},
{"domain":"ajnaanahata.eth"},
{"domain":"ajnas.eth"},
{"domain":"ajnayak.eth"},
{"domain":"ajneu.eth"},
{"domain":"ajnft.eth"},
{"domain":"ajnin.eth"},
{"domain":"ajnoguera.eth"},
{"domain":"ajo.eth"},
{"domain":"ajoe.eth"},
{"domain":"ajoe0x.eth"},
{"domain":"ajoea.eth"},
{"domain":"ajoel.eth"},
{"domain":"ajoey91.eth"},
{"domain":"ajogilvy.eth"},
{"domain":"ajohnson.eth"},
{"domain":"ajoker.eth"},
{"domain":"ajon915.eth"},
{"domain":"ajosemathew.eth"},
{"domain":"ajoseph.eth"},
{"domain":"ajoshr.eth"},
{"domain":"ajowens.eth"},
{"domain":"ajoymahato.eth"},
{"domain":"ajp.eth"},
{"domain":"ajp27.eth"},
{"domain":"ajpdigital.eth"},
{"domain":"ajphoto.eth"},
{"domain":"ajpicard.eth"},
{"domain":"ajpikul.eth"},
{"domain":"ajplut.eth"},
{"domain":"ajpprice.eth"},
{"domain":"ajprime.eth"},
{"domain":"ajpsystems.eth"},
{"domain":"ajr-photography.eth"},
{"domain":"ajrobertson.eth"},
{"domain":"ajroc.eth"},
{"domain":"ajrodriguez.eth"},
{"domain":"ajroyal.eth"},
{"domain":"ajs.eth"},
{"domain":"ajschaffer.eth"},
{"domain":"ajschokora.eth"},
{"domain":"ajsckjk.eth"},
{"domain":"ajseer.eth"},
{"domain":"ajsharp.eth"},
{"domain":"ajslavin.eth"},
{"domain":"ajslays.eth"},
{"domain":"ajsmining.eth"},
{"domain":"ajsol.eth"},
{"domain":"ajsperanza.eth"},
{"domain":"ajstetson.eth"},
{"domain":"ajt.eth"},
{"domain":"ajthegod.eth"},
{"domain":"ajthegreater.eth"},
{"domain":"ajthejuggalo.eth"},
{"domain":"ajtravel.eth"},
{"domain":"aju.eth"}
]}